connectedcarscomm/__init__.py
connectedcarscomm/constants.py
connectedcarscomm-0.1.0.dist-info/LICENSE
connectedcarscomm-0.1.0.dist-info/METADATA
connectedcarscomm-0.1.0.dist-info/WHEEL
connectedcarscomm-0.1.0.dist-info/top_level.txt
connectedcarscomm-0.1.0.dist-info/RECORD
