Metadata-Version: 2.1
Name: connectedcarscomm
Version: 0.1.0
Summary: Simple communication library for ConnectedCars.io
Home-page: https://github.com/heslegrave/connectedcarscomm
Author: Jais Heslegrave
Author-email: heslegrave@gmail.com
License: UNKNOWN
Keywords: ConnectedCars,Audi,Volkswagen,Skoda,SEAT
Platform: UNKNOWN
Classifier: Programming Language :: Python :: 3.7
Classifier: License :: OSI Approved :: MIT License
Requires-Python: >=3.7
